Workbook

Sheet How to use
B1: CareerPilot — Manual Test Plan
B2: End-to-end manual QA for the CareerPilot module, student and admin.
B3: Version 1.0 · 12 August 2026 · built against commit 1b5f0c3b
B6: WHAT IS IN THIS FILE
B7: Feature Guide | C7: Every feature explained — what it is, why it exists, when a student meets it, and where it lives. Read this before writing a single result.
B8: Test Cases | C8: The full suite. Filter by Module, Feature, Type or Priority. Fill in Result, Tested By, Date and Defect Ref as you go.
B9: Defect Log | C9: One row per defect found. Reference the Test Case ID.
B10: Summary | C10: Live counts. It reads the Test Cases sheet automatically — do not type into it.
B12: HOW TO RUN A PASS
B13: 1. Set up accounts | C13: You need FOUR: a brand-new unregistered mobile, a free member, a PAID member, and an admin. Most defects hide at the boundary between free and paid.
B14: 2. Work top to bottom | C14: Cases are ordered as a real student meets them. Running them out of order creates preconditions you do not have.
B15: 3. Record what you saw | C15: If a case fails, write what ACTUALLY happened in Actual Result. 'Failed' on its own cannot be fixed.
B16: 4. Raise the defect | C16: Log it in Defect Log and put its reference on the test case row.
B18: PRIORITIES
B19: P0 | C19: Blocks release. A student cannot complete a core journey, money is at risk, or data leaks.
B20: P1 | C20: Important. Works but is wrong, confusing, or fails on a common path.
B21: P2 | C21: Worth fixing. Cosmetic, rare, or an edge case with a workaround.
B23: CASE TYPES
B24: Positive | C24: The happy path — the thing works as intended for someone doing it correctly.
B25: Negative | C25: Wrong input, wrong state, wrong permission. The system must refuse clearly and safely.
B26: Corner | C26: Boundaries and collisions — midnight, expiry, concurrency, a rotated phone, a replayed request. This is where the real defects live.
B28: KNOWN GAPS — EXPECT THESE TO FAIL
B29: Price is ₹499 | C29: Production is configured at 499, not 1,599. TC-MEM-002 will fail until it is corrected.
B30: No interview quota | C30: 12 per member per year was specified but never implemented. TC-INT-006 will fail. It is an uncapped cost, not a cosmetic issue.
B31: Coins cannot be spent | C31: Earning works; spending does not exist. TC-CON-004 documents the expected state.
B32: 2 entitlements missing | C32: Production config holds 9 of 11 features. TC-CFG-004 will fail.
B33: 0 companies live | C33: Until a company clears the readiness bar, every Prepare Interviews and Mock Test case is blocked. Take Cognizant live first — it needs 10 more questions.
B34: Payment never tested | C34: No membership has ever been purchased in production. Treat TC-MEM-001 as the highest-risk case in this document.

Sheet Feature Guide
A1: # | B1: Module | C1: Feature | D1: What it is | E1: Why it exists | F1: When a student meets it | G1: Where it lives
A2: 1 | B2: Student | C2: Join, OTP & Login | D2: Registration by mobile with a WhatsApp OTP, plus password login once set. | E2: It is the front door. Everything else in CareerPilot is gated on an identity, and a stranger has to become a known member without a salesperson touching them. | F2: First contact — from an ad, a college drive, or a shared passport card. | G2: /careerpilot/join · /careerpilot/login
A3: 2 | B3: Student | C3: Career Readiness Assessment | D3: A free, deterministic (non-AI) assessment producing a career score, level and pathway. | E3: It is the hook and the qualifier. Free so anyone will start it; deterministic so it costs nothing to run at volume; scored so the paid roadmap feels earned rather than sold. | F3: Immediately after joining, before any payment is asked for. | G3: /careerpilot/assessment
A4: 3 | B4: Student | C4: Membership & Payment | D4: ₹1,599/year membership purchased through Razorpay, unlocking all paid entitlements. | E4: The only revenue event in the module. Everything upstream is designed to reach it and everything downstream is designed to justify it. | F4: When a student hits any paid feature, or from the result screen after the assessment. | G4: Any locked feature → Buy prompt → Razorpay checkout
A5: 4 | B5: Student | C5: Mission Control & Streak | D5: A daily set of missions with a streak counter and a nightly close job. | E5: A yearly membership dies without a reason to open the app on a Tuesday. The streak is the retention mechanic that turns a purchase into a habit. | F5: Every day, as the member's landing surface. | G5: /careerpilot
A6: 5 | B6: Student | C6: 90-Day Roadmap | D6: A personalised plan derived from the assessment. 7 days free, the full 90 paid. | E6: Converts a score into a plan. The paywall sits exactly where the value becomes obvious — the student can see the shape of the plan before being asked to pay for the rest. | F6: Straight after the assessment result, and revisited weekly. | G6: /careerpilot/roadmap
A7: 6 | B7: Student | C7: Practice — Coding, SQL, MCQ | D7: Runnable practice problems executed in a sandbox, with saved submissions. | E7: The daily habit that makes the membership feel used. Real execution, not multiple choice, because employers test code. | F7: Daily, usually alongside the day's mission. | G7: /careerpilot/practice · /careerpilot/practice/:id
A8: 7 | B8: Student | C8: Resume Centre | D8: Build, import, AI-improve and AI-score a resume. | E8: The artefact a student actually leaves with. It is the most tangible proof that the membership produced something. | F8: Before applications, and after major milestones. | G8: /careerpilot/resume
A9: 8 | B9: Student | C9: AI Mock Interview | D9: A spoken interview with an Indian-accented AI voice, short questions, stored feedback, optionally primed for a specific company. | E9: The headline feature and the main reason people pay. Interview nerves are the real blocker for most candidates, and rehearsal is the only cure. | F9: Once a student has a roadmap and some practice behind them; before real interviews. | G9: /careerpilot/interview
A10: 9 | B10: Student | C10: Prepare Interviews — Company Hub | D10: Per-company pages with six tabs: Overview, Interview Pattern, Salary, Mock Test, Mock Interview and Questions. A company is only visible once it clears the readiness bar. | E10: Students do not prepare 'for interviews', they prepare for TCS. Company-specific preparation is what they actually search for. | F10: In the weeks before a campus drive or an application. | G10: /careerpilot/companies · /careerpilot/companies/:slug
A11: 10 | B11: Student | C11: Company Mock Test | D11: A timed MCQ paper modelled on a company's real pattern, with a server-side clock. | E11: A rehearsal under the real clock. Knowing the questions is not the same as finishing in time, which is what actually eliminates candidates. | F11: After reading a company's pattern, before the real aptitude round. | G11: /careerpilot/companies/:slug → Mock Test → /careerpilot/mock-test/:id
A12: 11 | B12: Student | C12: Tech News | D12: A short daily feed of technology and hiring news, drafted by AI from a pasted URL. | E12: A cheap daily reason to return, and it makes the product feel alive between missions. | F12: Daily, in passing. | G12: /careerpilot/news
A13: 12 | B13: Student | C13: Coins, XP & Leaderboard | D13: XP for status, coins as currency, plus a global leaderboard and achievements. | E13: Motivation. XP marks progress that can never be taken away; coins are meant to be spent on rewards. NOTE FOR QA: the spending half is not built yet — coins can only be earned. | F13: Continuously, as a by-product of every other activity. | G13: /careerpilot/coins · /careerpilot/leaderboard · /careerpilot/achievements
... A22: 21 | B22: Admin | C22: Staging Board | D22: Moves a member between career stages. | E22: Stage drives which missions and content a member sees; it must be correctable without touching the database. | F22: When a member's situation changes. | G22: /admin/careerpilot/staging

Sheet Test Cases
A1: Test Case ID | B1: Module | C1: Feature | D1: Type | E1: Priority | F1: Test Case Title | G1: Preconditions | H1: Navigation Path | I1: Steps | J1: Test Data | K1: Expected Result | L1: Actual Result | M1: Result | N1: Tested By | O1: Date | P1: Defect Ref
A2: TC-JOIN-001 | B2: Student | C2: Join, OTP & Login | D2: Positive | E2: P0 | F2: Register a new member with a valid mobile | G2: Mobile number never used on this tenant | H2: Open /careerpilot/join | I2: 1. Open /careerpilot/join 2. Enter full name, mobile and email 3. Tap Send OTP 4. Read the OTP from WhatsApp 5. Enter it and tap Verify | J2: Name: Test Student Mobile: 9876500001 Email: test1@example.com | K2: OTP arrives on WhatsApp within 60s. After verifying, the member lands on the assessment start screen and a member record exists in Admin > Members.
A3: TC-JOIN-002 | B3: Student | C3: Join, OTP & Login | D3: Positive | E3: P1 | F3: Log in with OTP on a returning member | G3: Member already registered | H3: Open /careerpilot/login | I3: 1. Open /careerpilot/login 2. Enter the registered mobile 3. Tap Send OTP 4. Enter the OTP | J3: Mobile: 9876500001 | K3: Member is logged in and lands on /careerpilot with their existing progress intact — not a fresh assessment.
A4: TC-JOIN-003 | B4: Student | C4: Join, OTP & Login | D4: Positive | E4: P1 | F4: Set a password and then log in with it | G4: Member logged in via OTP, no password set | H4: /careerpilot → Profile → Set password | I4: 1. Set a password of 8+ characters 2. Log out 3. Open /careerpilot/login 4. Switch to password login 5. Enter mobile and password | J4: Password: Test@2026 | K4: Password is accepted, login succeeds without an OTP, and the session behaves identically to an OTP login.
A5: TC-JOIN-004 | B5: Student | C5: Join, OTP & Login | D5: Positive | E5: P2 | F5: Resend OTP after the timer expires | G5: OTP requested, countdown finished | H5: /careerpilot/join → OTP screen | I5: 1. Request an OTP 2. Wait for the resend timer to reach zero 3. Tap Resend | J5: - | K5: A new OTP is sent and accepted. The previous OTP is rejected.
A6: TC-JOIN-005 | B6: Student | C6: Join, OTP & Login | D6: Negative | E6: P0 | F6: Reject an invalid mobile number | G6: - | H6: /careerpilot/join | I6: 1. Enter a 9-digit number 2. Tap Send OTP | J6: Mobile: 987650000 | K6: A clear inline message states the number must be a valid 10-digit Indian mobile. No OTP is sent and no member record is created.
A7: TC-JOIN-006 | B7: Student | C7: Join, OTP & Login | D7: Negative | E7: P0 | F7: Reject a wrong OTP | G7: OTP requested | H7: /careerpilot/join → OTP screen | I7: 1. Enter six digits that are not the OTP 2. Tap Verify | J7: OTP: 000000 | K7: Verification fails with a readable message. The member is NOT logged in and no session token is issued.
A8: TC-JOIN-007 | B8: Student | C8: Join, OTP & Login | D8: Negative | E8: P1 | F8: Reject an expired OTP | G8: OTP requested | H8: /careerpilot/join → OTP screen | I8: 1. Request an OTP 2. Wait past the expiry window 3. Enter the original OTP | J8: - | K8: Verification is refused as expired and the member is invited to request a new one.
A9: TC-JOIN-008 | B9: Student | C9: Join, OTP & Login | D9: Negative | E9: P1 | F9: Reject a password under the minimum length | G9: Member logged in | H9: /careerpilot → Profile | I9: 1. Enter a 5-character password 2. Save | J9: Password: Ab1@x | K9: Save is refused with a message naming the 8-character minimum. No password is stored.
A10: TC-JOIN-009 | B10: Student | C10: Join, OTP & Login | D10: Corner | E10: P1 | F10: Mobile entered with +91, spaces or dashes | G10: - | H10: /careerpilot/join | I10: 1. Enter the same number in four formats 2. Send OTP each time | J10: +91 98765 00001 +919876500001 098765-00001 9876500001 | K10: All four normalise to the SAME member. No duplicate accounts are created. (This was a real defect — three different normalisers existed.)
A11: TC-JOIN-010 | B11: Student | C11: Join, OTP & Login | D11: Corner | E11: P2 | F11: Same mobile registers twice | G11: Member already exists | H11: /careerpilot/join | I11: 1. Register with an existing mobile 2. Complete the OTP | J11: Mobile: 9876500001 | K11: The existing member is logged in rather than a duplicate being created. Progress is preserved.
A12: TC-JOIN-011 | B12: Student | C12: Join, OTP & Login | D12: Corner | E12: P2 | F12: OTP requested many times in quick succession | G12: - | H12: /careerpilot/join | I12: 1. Tap Send OTP repeatedly, as fast as the UI allows | J12: - | K12: Requests are throttled. The button disables or a cooldown message appears. WhatsApp is not spammed and cost is bounded.
A13: TC-ASM-001 | B13: Student | C13: Career Readiness Assessment | D13: Positive | E13: P0 | F13: Complete the assessment end to end | G13: Newly registered member | H13: /careerpilot/assessment | I13: 1. Start the assessment 2. Answer every question across all stage segments 3. Submit | J13: Answer honestly as a final-year student | K13: A career score, level and pathway are shown. The result is reproducible — the same answers always give the same score, because scoring is deterministic.
... A139: TC-MOB-004 | B139: Both | C139: Cross-cutting — Mobile | D139: Corner | E139: P2 | F139: Mock interview on mobile data | G139: Paid member on 4G | H139: /careerpilot/interview | I139: 1. Run a full interview on mobile data, not wifi | J139: - | K139: Audio plays and answers upload. Slow networks degrade gracefully rather than hanging.

Sheet Defect Log
A1: Defect ID | B1: Test Case ID | C1: Module | D1: Summary | E1: Steps to Reproduce | F1: Expected | G1: Actual | H1: Severity | I1: Status | J1: Raised By | K1: Date | L1: Notes
A2: DEF-001 | B2: TC-MEM-002 | C2: Student | D2: Membership price is ₹499 in production, not ₹1,599 | E2: Open any locked feature as a free member and read the price on the prompt. | F2: ₹1,599 everywhere | G2: ₹499 — passportconfigs.priceInr is 499 | H2: Critical | I2: Open | J2: Audit | K2: 12-Aug-2026 | L2: Config only, no code change. Fix before any demo.
A3: DEF-002 | B3: TC-INT-006 | C3: Student | D3: No 12-per-year cap on mock interviews | E3: As a paid member, run interviews repeatedly. No limit is applied. | F3: 13th attempt refused | G3: Unlimited interviews allowed | H3: Critical | I3: Open | J3: Audit | K3: 12-Aug-2026 | L3: Uncapped AI cost at ~₹2.42 per interview.
A4: DEF-003 | B4: TC-CON-004 | C4: Student | D4: Coins can be earned but never spent | E4: Earn coins, then look for any redemption path. | F4: A catalogue or redemption flow | G4: No spend path exists anywhere | H4: Major | I4: Open | J4: Audit | K4: 12-Aug-2026 | L4: No spendCoins function and no redeem endpoint.
A5: DEF-004 | B5: TC-CFG-004 | C5: Admin | D5: Entitlements config holds 9 of 11 features | E5: Open /admin/passport/config and count the rows. | F5: 11 rows including Tech News and Company Questions | G5: 9 rows — the two newest are absent | H5: Major | I5: Open | J5: Audit | K5: 12-Aug-2026 | L5: Defaults apply only at document creation.
A6: DEF-005 | B6: TC-COMP-001 | C6: Student | D6: No company is live, so Prepare Interviews is empty | E6: Open /careerpilot/companies as a paid member. | F6: At least one company listed | G6: Empty list — all 20 below the readiness bar | H6: Major | I6: Open | J6: Audit | K6: 12-Aug-2026 | L6: Content, not code. Cognizant needs 10 more questions.

Sheet Summary
B1: Execution Summary
B2: Formulas read the Test Cases sheet. Do not type into the counts.
B4: BY RESULT
B5: Total | C5: Pass | D5: Fail | E5: Blocked | F5: Not Run | G5: % Executed | H5: % Passed
B6: 138 | C6: =COUNTIF('Test Cases'!M2:M139,"Pass") | D6: =COUNTIF('Test Cases'!M2:M139,"Fail") | E6: =COUNTIF('Test Cases'!M2:M139,"Blocked") | F6: =B6-C6-D6-E6 | G6: =IF(B6=0,0,(C6+D6+E6)/B6) | H6: =IF((C6+D6)=0,0,C6/(C6+D6))
B9: BY TYPE
B10: Type | C10: Total | D10: Pass | E10: Fail
B11: Positive | C11: =COUNTIF('Test Cases'!D2:D139,B11) | D11: =COUNTIFS('Test Cases'!D2:D139,B11,'Test Cases'!M2:M139,"Pass") | E11: =COUNTIFS('Test Cases'!D2:D139,B11,'Test Cases'!M2:M139,"Fail")
B12: Negative | C12: =COUNTIF('Test Cases'!D2:D139,B12) | D12: =COUNTIFS('Test Cases'!D2:D139,B12,'Test Cases'!M2:M139,"Pass") | E12: =COUNTIFS('Test Cases'!D2:D139,B12,'Test Cases'!M2:M139,"Fail")
B13: Corner | C13: =COUNTIF('Test Cases'!D2:D139,B13) | D13: =COUNTIFS('Test Cases'!D2:D139,B13,'Test Cases'!M2:M139,"Pass") | E13: =COUNTIFS('Test Cases'!D2:D139,B13,'Test Cases'!M2:M139,"Fail")
B15: BY PRIORITY
B16: Priority | C16: Total | D16: Pass | E16: Fail
B17: P0 | C17: =COUNTIF('Test Cases'!E2:E139,B17) | D17: =COUNTIFS('Test Cases'!E2:E139,B17,'Test Cases'!M2:M139,"Pass") | E17: =COUNTIFS('Test Cases'!E2:E139,B17,'Test Cases'!M2:M139,"Fail")
B18: P1 | C18: =COUNTIF('Test Cases'!E2:E139,B18) | D18: =COUNTIFS('Test Cases'!E2:E139,B18,'Test Cases'!M2:M139,"Pass") | E18: =COUNTIFS('Test Cases'!E2:E139,B18,'Test Cases'!M2:M139,"Fail")
B19: P2 | C19: =COUNTIF('Test Cases'!E2:E139,B19) | D19: =COUNTIFS('Test Cases'!E2:E139,B19,'Test Cases'!M2:M139,"Pass") | E19: =COUNTIFS('Test Cases'!E2:E139,B19,'Test Cases'!M2:M139,"Fail")
B21: BY FEATURE
B22: Feature | C22: Total | D22: Pass | E22: Fail
B23: Join, OTP & Login | C23: =COUNTIF('Test Cases'!C2:C139,B23) | D23: =COUNTIFS('Test Cases'!C2:C139,B23,'Test Cases'!M2:M139,"Pass") | E23: =COUNTIFS('Test Cases'!C2:C139,B23,'Test Cases'!M2:M139,"Fail")
B24: Career Readiness Assessment | C24: =COUNTIF('Test Cases'!C2:C139,B24) | D24: =COUNTIFS('Test Cases'!C2:C139,B24,'Test Cases'!M2:M139,"Pass") | E24: =COUNTIFS('Test Cases'!C2:C139,B24,'Test Cases'!M2:M139,"Fail")
B25: Membership & Payment | C25: =COUNTIF('Test Cases'!C2:C139,B25) | D25: =COUNTIFS('Test Cases'!C2:C139,B25,'Test Cases'!M2:M139,"Pass") | E25: =COUNTIFS('Test Cases'!C2:C139,B25,'Test Cases'!M2:M139,"Fail")
B26: Mission Control & Streak | C26: =COUNTIF('Test Cases'!C2:C139,B26) | D26: =COUNTIFS('Test Cases'!C2:C139,B26,'Test Cases'!M2:M139,"Pass") | E26: =COUNTIFS('Test Cases'!C2:C139,B26,'Test Cases'!M2:M139,"Fail")
B27: 90-Day Roadmap | C27: =COUNTIF('Test Cases'!C2:C139,B27) | D27: =COUNTIFS('Test Cases'!C2:C139,B27,'Test Cases'!M2:M139,"Pass") | E27: =COUNTIFS('Test Cases'!C2:C139,B27,'Test Cases'!M2:M139,"Fail")
B28: Practice — Coding, SQL, MCQ | C28: =COUNTIF('Test Cases'!C2:C139,B28) | D28: =COUNTIFS('Test Cases'!C2:C139,B28,'Test Cases'!M2:M139,"Pass") | E28: =COUNTIFS('Test Cases'!C2:C139,B28,'Test Cases'!M2:M139,"Fail")
B29: Resume Centre | C29: =COUNTIF('Test Cases'!C2:C139,B29) | D29: =COUNTIFS('Test Cases'!C2:C139,B29,'Test Cases'!M2:M139,"Pass") | E29: =COUNTIFS('Test Cases'!C2:C139,B29,'Test Cases'!M2:M139,"Fail")
B30: AI Mock Interview | C30: =COUNTIF('Test Cases'!C2:C139,B30) | D30: =COUNTIFS('Test Cases'!C2:C139,B30,'Test Cases'!M2:M139,"Pass") | E30: =COUNTIFS('Test Cases'!C2:C139,B30,'Test Cases'!M2:M139,"Fail")
B31: Prepare Interviews — Company Hub | C31: =COUNTIF('Test Cases'!C2:C139,B31) | D31: =COUNTIFS('Test Cases'!C2:C139,B31,'Test Cases'!M2:M139,"Pass") | E31: =COUNTIFS('Test Cases'!C2:C139,B31,'Test Cases'!M2:M139,"Fail")
B32: Company Mock Test | C32: =COUNTIF('Test Cases'!C2:C139,B32) | D32: =COUNTIFS('Test Cases'!C2:C139,B32,'Test Cases'!M2:M139,"Pass") | E32: =COUNTIFS('Test Cases'!C2:C139,B32,'Test Cases'!M2:M139,"Fail")
B33: Tech News | C33: =COUNTIF('Test Cases'!C2:C139,B33) | D33: =COUNTIFS('Test Cases'!C2:C139,B33,'Test Cases'!M2:M139,"Pass") | E33: =COUNTIFS('Test Cases'!C2:C139,B33,'Test Cases'!M2:M139,"Fail")
B34: Coins, XP & Leaderboard | C34: =COUNTIF('Test Cases'!C2:C139,B34) | D34: =COUNTIFS('Test Cases'!C2:C139,B34,'Test Cases'!M2:M139,"Pass") | E34: =COUNTIFS('Test Cases'!C2:C139,B34,'Test Cases'!M2:M139,"Fail")
B35: Public Passport Card | C35: =COUNTIF('Test Cases'!C2:C139,B35) | D35: =COUNTIFS('Test Cases'!C2:C139,B35,'Test Cases'!M2:M139,"Pass") | E35: =COUNTIFS('Test Cases'!C2:C139,B35,'Test Cases'!M2:M139,"Fail")
B36: Plan & Entitlements Config | C36: =COUNTIF('Test Cases'!C2:C139,B36) | D36: =COUNTIFS('Test Cases'!C2:C139,B36,'Test Cases'!M2:M139,"Pass") | E36: =COUNTIFS('Test Cases'!C2:C139,B36,'Test Cases'!M2:M139,"Fail")
B37: Assessment Builder & Paper Design | C37: =COUNTIF('Test Cases'!C2:C139,B37) | D37: =COUNTIFS('Test Cases'!C2:C139,B37,'Test Cases'!M2:M139,"Pass") | E37: =COUNTIFS('Test Cases'!C2:C139,B37,'Test Cases'!M2:M139,"Fail")
B38: Pathways & Missions | C38: =COUNTIF('Test Cases'!C2:C139,B38) | D38: =COUNTIFS('Test Cases'!C2:C139,B38,'Test Cases'!M2:M139,"Pass") | E38: =COUNTIFS('Test Cases'!C2:C139,B38,'Test Cases'!M2:M139,"Fail")
B39: Members Admin | C39: =COUNTIF('Test Cases'!C2:C139,B39) | D39: =COUNTIFS('Test Cases'!C2:C139,B39,'Test Cases'!M2:M139,"Pass") | E39: =COUNTIFS('Test Cases'!C2:C139,B39,'Test Cases'!M2:M139,"Fail")
B40: Company Roster & Content | C40: =COUNTIF('Test Cases'!C2:C139,B40) | D40: =COUNTIFS('Test Cases'!C2:C139,B40,'Test Cases'!M2:M139,"Pass") | E40: =COUNTIFS('Test Cases'!C2:C139,B40,'Test Cases'!M2:M139,"Fail")
B41: Tech News Admin | C41: =COUNTIF('Test Cases'!C2:C139,B41) | D41: =COUNTIFS('Test Cases'!C2:C139,B41,'Test Cases'!M2:M139,"Pass") | E41: =COUNTIFS('Test Cases'!C2:C139,B41,'Test Cases'!M2:M139,"Fail")
B42: Coins Admin | C42: =COUNTIF('Test Cases'!C2:C139,B42) | D42: =COUNTIFS('Test Cases'!C2:C139,B42,'Test Cases'!M2:M139,"Pass") | E42: =COUNTIFS('Test Cases'!C2:C139,B42,'Test Cases'!M2:M139,"Fail")
B43: Staging Board | C43: =COUNTIF('Test Cases'!C2:C139,B43) | D43: =COUNTIFS('Test Cases'!C2:C139,B43,'Test Cases'!M2:M139,"Pass") | E43: =COUNTIFS('Test Cases'!C2:C139,B43,'Test Cases'!M2:M139,"Fail")
B44: Cross-cutting — Access & Security | C44: =COUNTIF('Test Cases'!C2:C139,B44) | D44: =COUNTIFS('Test Cases'!C2:C139,B44,'Test Cases'!M2:M139,"Pass") | E44: =COUNTIFS('Test Cases'!C2:C139,B44,'Test Cases'!M2:M139,"Fail")
B45: Cross-cutting — Mobile | C45: =COUNTIF('Test Cases'!C2:C139,B45) | D45: =COUNTIFS('Test Cases'!C2:C139,B45,'Test Cases'!M2:M139,"Pass") | E45: =COUNTIFS('Test Cases'!C2:C139,B45,'Test Cases'!M2:M139,"Fail")
